{
  "_id": "niCnWPx18Nekw5jj",
  "name": "Size",
  "type": "feat",
  "img": "systems/sw5e/packs/Icons/Species/Dowutin-Young.webp",
  "effects": [],
  "folder": null,
  "sort": 0,
  "flags": {
    "betterRollssw5e": {
      "critRange": {
        "type": "String",
        "value": ""
      },
      "critDamage": {
        "type": "String",
        "value": ""
      },
      "quickDesc": {
        "type": "Boolean",
        "value": true,
        "altValue": true
      },
      "quickAttack": {
        "type": "Boolean",
        "value": true,
        "altValue": true
      },
      "quickSave": {
        "type": "Boolean",
        "value": true,
        "altValue": true
      },
      "quickDamage": {
        "type": "Array",
        "value": [],
        "altValue": [],
        "context": []
      },
      "quickProperties": {
        "type": "Boolean",
        "value": true,
        "altValue": true
      },
      "quickCharges": {
        "type": "Boolean",
        "value": {
          "use": true,
          "resource": true,
          "charge": true
        },
        "altValue": {
          "use": true,
          "resource": true,
          "charge": true
        }
      },
      "quickTemplate": {
        "type": "Boolean",
        "value": true,
        "altValue": true
      },
      "quickOther": {
        "type": "Boolean",
        "value": true,
        "altValue": true,
        "context": ""
      },
      "quickFlavor": {
        "type": "Boolean",
        "value": true,
        "altValue": true
      },
      "quickPrompt": {
        "type": "Boolean",
        "value": false,
        "altValue": false
      }
    },
    "sw5e-importer": {
      "timestamp": "2022-10-18T11:21:19.5029237+00:00",
      "importer_version": 3,
      "uid": "Feature.name-size.source-species.sourceName-dowutin_young.level-None"
    }
  },
  "system": {
    "description": {
      "value": "<p>Dowutins have a unique special characteristic; from birth to death, they never stop growing. Even as an adolescent, dowutins tend to tower over other species, reaching heights over 8 feet and weighing 400 pounds. Regardless of your position in that range, your size is Medium.</p>",
      "chat": "",
      "unidentified": ""
    },
    "requirements": "None (Dowutin, Young)",
    "source": "EC",
    "activation": {
      "type": null,
      "cost": null,
      "condition": ""
    },
    "duration": {
      "value": null,
      "units": "inst"
    },
    "cover": null,
    "target": {
      "value": null,
      "width": null,
      "units": "",
      "type": ""
    },
    "range": {
      "value": null,
      "long": null,
      "units": "",
      "unit": ""
    },
    "uses": {
      "value": null,
      "max": null,
      "per": null,
      "recovery": ""
    },
    "consume": {
      "type": "",
      "target": null,
      "amount": null
    },
    "ability": null,
    "actionType": "other",
    "attackBonus": 0,
    "chatFlavor": "",
    "critical": {
      "threshold": null,
      "damage": null
    },
    "damage": {
      "parts": [],
      "versatile": ""
    },
    "formula": "",
    "save": {
      "ability": "",
      "dc": null,
      "scaling": "power"
    },
    "type": {
      "value": "species",
      "subtype": ""
    },
    "recharge": {
      "value": null,
      "charged": false
    },
    "className": null
  },
  "ownership": {
    "default": 0
  },
  "_stats": {
    "systemId": "sw5e",
    "systemVersion": "2.1.5.2.4.0",
    "coreVersion": "10.291",
    "createdTime": 1674494003652,
    "modifiedTime": 1678471093438,
    "lastModifiedBy": "sw5ebuilder0000"
  }
}
