{
  "_id": "ulrqYwkLir7OmJQJ",
  "name": "Tech Amateur",
  "type": "feat",
  "img": "systems/sw5e/packs/Icons/Class%20Features/SCLR-Passive.webp",
  "effects": [],
  "folder": null,
  "sort": 0,
  "flags": {
    "sw5e-importer": {
      "timestamp": "2023-03-09T01:51:57.6296276+00:00",
      "importer_version": 3,
      "uid": "Feature.name-tech_amateur.source-classinvocation.sourceName-scholar.level-None"
    }
  },
  "system": {
    "description": {
      "value": "<p>You learn and can cast one 1st-level tech power once per long rest. Your techcasting ability is Intelligence. You require use of a wristpad for this power.</p>\n<p>You can select this discovery multiple times. Each time you do so, you must choose a different power.</p>",
      "chat": "",
      "unidentified": ""
    },
    "requirements": "Scholar",
    "source": "PHB",
    "activation": {
      "type": null,
      "cost": null,
      "condition": ""
    },
    "duration": {
      "value": null,
      "units": "inst"
    },
    "cover": null,
    "crewed": false,
    "target": {
      "value": null,
      "width": null,
      "units": "",
      "type": ""
    },
    "range": {
      "value": null,
      "long": null,
      "units": "",
      "unit": ""
    },
    "uses": {
      "value": null,
      "max": null,
      "per": null,
      "recovery": ""
    },
    "consume": {
      "type": "",
      "target": null,
      "amount": null
    },
    "ability": null,
    "actionType": "other",
    "attackBonus": 0,
    "chatFlavor": "",
    "critical": null,
    "damage": {
      "parts": [],
      "versatile": ""
    },
    "formula": "",
    "save": {
      "ability": "",
      "dc": null,
      "scaling": "power"
    },
    "type": {
      "value": "class",
      "subtype": "scholarInvocation"
    },
    "recharge": {
      "value": null,
      "charged": false
    },
    "attributes": {
      "speed": {
        "space": null,
        "turn": null
      }
    },
    "className": null
  },
  "ownership": {
    "default": 0
  },
  "_stats": {
    "systemId": "sw5e",
    "systemVersion": "2.3.1.2.6.4",
    "coreVersion": "11.315",
    "createdTime": 1674493981243,
    "modifiedTime": 1699591665879,
    "lastModifiedBy": "sw5ebuilder0000"
  },
  "_key": "!items!ulrqYwkLir7OmJQJ"
}
