{
  "name": "Natural Empathy",
  "flags": {
    "sw5e-importer": {
      "timestamp": "2023-03-09T01:52:12.7088851+00:00",
      "importer_version": 3,
      "uid": "Feature.name-natural_empathy.source-species.sourceName-quermian.level-None"
    }
  },
  "type": "feat",
  "img": "systems/sw5e/packs/Icons/Species/Quermian.webp",
  "effects": [],
  "system": {
    "description": {
      "value": "<p>Quermians' talent at reading the body language of others allow them to sense the emotions in those around them. You have advantage on Wisdom (Insight) checks to determine emotions against humanoids and beasts within 10 feet of you.</p>",
      "chat": "",
      "unidentified": ""
    },
    "requirements": "Quermian",
    "source": "EC",
    "activation": {
      "type": null,
      "cost": null,
      "condition": ""
    },
    "duration": {
      "value": null,
      "units": "inst"
    },
    "cover": null,
    "crewed": false,
    "target": {
      "value": null,
      "width": null,
      "units": "",
      "type": ""
    },
    "range": {
      "value": "10",
      "long": null,
      "units": "",
      "unit": "feet"
    },
    "uses": {
      "value": null,
      "max": null,
      "per": null,
      "recovery": ""
    },
    "consume": {
      "type": "",
      "target": null,
      "amount": null
    },
    "ability": null,
    "actionType": "other",
    "attackBonus": 0,
    "chatFlavor": "",
    "critical": {
      "threshold": null,
      "damage": ""
    },
    "damage": {
      "parts": [],
      "versatile": ""
    },
    "formula": "",
    "save": {
      "ability": "",
      "dc": null,
      "scaling": "power"
    },
    "type": {
      "value": "species",
      "subtype": ""
    },
    "recharge": {
      "value": null,
      "charged": false
    },
    "attributes": {
      "speed": {
        "space": null,
        "turn": null
      }
    },
    "className": null
  },
  "folder": null,
  "sort": 0,
  "ownership": {
    "default": 0
  },
  "_stats": {
    "systemId": "sw5e",
    "systemVersion": "2.3.1.2.6.1",
    "coreVersion": "11.308",
    "createdTime": 1667426106908,
    "modifiedTime": 1695981492641,
    "lastModifiedBy": "sw5ebuilder0000"
  },
  "_id": "KNDjtni0NH5ym2Os",
  "_key": "!items!KNDjtni0NH5ym2Os"
}
