{
  "name": "Saberstaff",
  "flags": {
    "sw5e-importer": {
      "timestamp": "2023-05-30T20:15:25.5767259+00:00",
      "importer_version": 3,
      "uid": "Weapon.name-saberstaff.equipmentCategory-weapon"
    }
  },
  "type": "weapon",
  "img": "systems/sw5e/packs/Icons/Exotic%20Lightweapons/Saberstaff.webp",
  "effects": [],
  "system": {
    "description": {
      "value": "<h3>Modal (double-saber and tech-staff)</h3>\n<p>A weapon with this property can switch between modes. A list of weapons in parentheses appears with the property-the weapons between which an exotic weapon can be switched by using an object interaction.</p>",
      "chat": "",
      "unidentified": ""
    },
    "requirements": "",
    "source": "EC",
    "quantity": 1,
    "weight": 0,
    "price": {
      "value": 1375,
      "denomination": "gc"
    },
    "attunement": 0,
    "equipped": false,
    "rarity": "",
    "identified": true,
    "isCargo": false,
    "activation": {
      "type": "action",
      "cost": 1,
      "condition": ""
    },
    "duration": {
      "value": null,
      "units": ""
    },
    "cover": null,
    "crewed": false,
    "target": {
      "value": 1,
      "width": null,
      "units": "",
      "type": "enemy"
    },
    "range": {
      "value": null,
      "long": null,
      "units": "ft"
    },
    "uses": {
      "value": null,
      "max": null,
      "per": null,
      "recovery": ""
    },
    "consume": {
      "type": "",
      "target": "",
      "amount": null,
      "ammount": null
    },
    "ability": "",
    "actionType": "mwak",
    "attackBonus": 0,
    "chatFlavor": "",
    "critical": {
      "threshold": null,
      "damage": ""
    },
    "damage": {
      "parts": [],
      "versatile": ""
    },
    "formula": "",
    "save": {
      "ability": "",
      "dc": null,
      "scaling": "power"
    },
    "armor": {
      "value": 10
    },
    "hp": {
      "value": 0,
      "max": 0,
      "dt": null,
      "conditions": ""
    },
    "modify": {
      "chassis": "none",
      "augmentSlots": 0,
      "modSlots": 4,
      "items": [],
      "changes": {},
      "type": null
    },
    "weaponType": "exoticLW",
    "weaponClass": "",
    "baseItem": "saberstaff",
    "ammo": {
      "target": null,
      "value": null,
      "use": null,
      "types": []
    },
    "properties": {
      "dou": true,
      "-=amm": null
    },
    "proficient": null
  },
  "folder": null,
  "sort": 0,
  "ownership": {
    "default": 0
  },
  "_stats": {
    "systemId": "sw5e",
    "systemVersion": "2.3.1.2.6.4",
    "coreVersion": "11.308",
    "createdTime": 1667426099440,
    "modifiedTime": 1698778731086,
    "lastModifiedBy": "sw5ebuilder0000"
  },
  "_id": "8VjKAKu1UfvGU3t5",
  "_key": "!items!8VjKAKu1UfvGU3t5"
}
