{
  "_id": "A4u1vnQHssjTs3r7",
  "name": "Mounted Specialist",
  "type": "archetype",
  "img": "systems/sw5e/packs/Icons/Archetypes/MountedSpecialist.webp",
  "effects": [],
  "folder": null,
  "sort": 0,
  "flags": {
    "sw5e-importer": {
      "timestamp": "2023-03-09T01:52:15.1704569+00:00",
      "importer_version": 3,
      "uid": "Archetype.name-mounted_specialist"
    }
  },
  "system": {
    "description": {
      "value": "<h1>Mounted Specialist</h1>\n<p>Those fighters who choose to become Mounted Specialists excel at mounted combat. Mounted Specialists are most dangerous from the seat of a speeder or saddle of a varactyl, though they can hold their own from the ground. Their versatility often has them leading the charge or protecting the team.</p>",
      "chat": ""
    },
    "source": {
      "custom": "EC"
    },
    "identifier": "mountedspecialist",
    "classIdentifier": "fighter",
    "advancement": [
      {
        "_id": "2GKm2C78SdZ956OK",
        "type": "ItemGrant",
        "configuration": {
          "items": [
            {
              "uuid": "Compendium.sw5e.archetypefeatures.iz1mFVwi75BeR9sO",
              "optional": false
            },
            {
              "uuid": "Compendium.sw5e.archetypefeatures.SdWUpUE4k0vBs2SC",
              "optional": false
            },
            {
              "uuid": "Compendium.sw5e.archetypefeatures.y0TGb6fXDhT7U2ns",
              "optional": false
            }
          ],
          "optional": false,
          "power": null
        },
        "value": {},
        "level": 3,
        "title": "Features"
      },
      {
        "_id": "oFbnPaDnL7J1PtUp",
        "type": "ItemGrant",
        "configuration": {
          "items": [
            {
              "uuid": "Compendium.sw5e.archetypefeatures.SAaO6mBqJ3BYqAPv",
              "optional": false
            }
          ],
          "optional": false,
          "power": null
        },
        "value": {},
        "level": 7,
        "title": "Features"
      },
      {
        "_id": "1wwG8Sbb01L31Q5S",
        "type": "ItemGrant",
        "configuration": {
          "items": [
            {
              "uuid": "Compendium.sw5e.archetypefeatures.O2CRg1S8z4bo9s9j",
              "optional": false
            }
          ],
          "optional": false,
          "power": null
        },
        "value": {},
        "level": 10,
        "title": "Features"
      },
      {
        "_id": "dLYv5Rd2Pw4akAyp",
        "type": "ItemGrant",
        "configuration": {
          "items": [
            {
              "uuid": "Compendium.sw5e.archetypefeatures.nmFUs2mLNxFsuY6k",
              "optional": false
            }
          ],
          "optional": false,
          "power": null
        },
        "value": {},
        "level": 15,
        "title": "Features"
      },
      {
        "_id": "1s5EendL5G8I1wuo",
        "type": "ItemGrant",
        "configuration": {
          "items": [
            {
              "uuid": "Compendium.sw5e.archetypefeatures.u7MxfRLGGRYAy04z",
              "optional": false
            }
          ],
          "optional": false,
          "power": null
        },
        "value": {},
        "level": 18,
        "title": "Features"
      },
      {
        "_id": "1mPFuBtarB8i1B7c",
        "type": "Trait",
        "configuration": {
          "choices": [
            {
              "count": 1,
              "pool": [
                "skills:ani",
                "skills:pil"
              ]
            }
          ],
          "grants": [],
          "mode": "default",
          "allowReplacements": false
        },
        "value": {
          "chosen": []
        },
        "level": 3
      }
    ],
    "powercasting": {
      "force": "none",
      "forceOverride": "",
      "tech": "none",
      "techOverride": ""
    },
    "superiority": {
      "progression": 0
    }
  },
  "ownership": {
    "default": 0
  },
  "_stats": {
    "systemId": "sw5e",
    "systemVersion": "3.2.1.2.8.0",
    "coreVersion": "11.315",
    "createdTime": 1674493959719,
    "modifiedTime": 1720552689111,
    "lastModifiedBy": "sw5ebuilder00000"
  },
  "_key": "!items!A4u1vnQHssjTs3r7"
}
