{
  "_id": "q77zsiObxfzRNWUF",
  "name": "Shistavanen",
  "type": "species",
  "img": "systems/sw5e/packs/Icons/Species/Shistavanen.webp",
  "effects": [
    {
      "_id": "uIcJ7M92lT53GK8n",
      "changes": [
        {
          "key": "system.details.species",
          "value": "Shistavanen",
          "mode": 5,
          "priority": 5
        },
        {
          "key": "system.traits.size",
          "value": "med",
          "mode": 5,
          "priority": 5
        },
        {
          "key": "system.attributes.movement.walk",
          "value": "30",
          "mode": 5,
          "priority": 5
        },
        {
          "key": "system.attributes.senses.darkvision",
          "value": "60",
          "mode": 2,
          "priority": 20
        },
        {
          "key": "system.traits.languages.value",
          "value": "basic",
          "mode": 0,
          "priority": 0
        },
        {
          "key": "system.traits.languages.value",
          "value": "shistavanen",
          "mode": 0,
          "priority": 0
        },
        {
          "key": "flags.sw5e.keenSenses",
          "value": "1",
          "mode": 0,
          "priority": 20
        },
        {
          "key": "flags.sw5e.regenerative",
          "value": "1",
          "mode": 0,
          "priority": 20
        }
      ],
      "disabled": false,
      "duration": {
        "startTime": null,
        "seconds": null,
        "combat": null,
        "rounds": null,
        "turns": null,
        "startRound": null,
        "startTurn": null
      },
      "icon": "systems/sw5e/packs/Icons/Species/Shistavanen.webp",
      "tint": null,
      "transfer": true,
      "flags": {},
      "origin": null,
      "name": "Shistavanen",
      "description": "",
      "statuses": [],
      "_key": "!items.effects!q77zsiObxfzRNWUF.uIcJ7M92lT53GK8n",
      "sort": 0
    }
  ],
  "folder": null,
  "sort": 0,
  "flags": {
    "sw5e-importer": {
      "timestamp": "2023-03-09T01:52:12.291126+00:00",
      "importer_version": 3,
      "uid": "Species.name-shistavanen"
    }
  },
  "system": {
    "data": "$characteristics-table",
    "description": {
      "value": "<h2>Biology and Appearance</h2>\n<p>Shistavanen have pronounced muzzles, sharp claws, long pointed teeth, and pointed ears set on top of their heads. Shistavanen also possess large glowing eyes, and can also run at high speeds for long periods without getting tired, alternately using two or four limbs. As predators, they possess keen hearing and smell and excellent night vision.</p>\n<h2>Society and Culture</h2>\n<p>As a species, the Shistavanen are isolationists. The species colonized all the unpopulated worlds in the Uvena system to prevent them from being settled by non-Shistavanen, and their restrictive trade laws (which are unapologetic in how they favor their own kind over off-world traders).  Most of their society uses technology similar to the rest of the galaxy, though some parts of Uvena Prime use slightly less sophisticated technology.</p>\n<p>A minority of Shistavanen are more outgoing, and travel the galaxy's hyperlanes. Even these Shistavanen usually remain by themselves or with other Shistavanen. Due to their natural predatory instincts, Shistavanen commonly find employment as scouts, mercenaries and bounty hunters. Many other species react badly to Shistavanen, since their isolationist culture makes them an unfamiliar sight, and their predatory appearance put other species on edge.</p>\n<h2>Names</h2>\n<p>Shistavanen first names typically sound graceful, while their surnames are more gutteral. Surnames are familial.</p>\n<p><strong>Male Names.</strong> Bustuc, Hulvav, Kembol, Nemdav, Sirul</p>\n<p><strong>Female Names.</strong> Gaeft, Laer, Recloz, Shaalir, Thovnim</p>\n<p><strong>Surnames.</strong> Ghirat, Lakrevl, Meq, Nukroft, Rosk</p>",
      "chat": "",
      "unidentified": ""
    },
    "traits": "",
    "source": "EC",
    "identifier": "shistavanen",
    "advancement": [
      {
        "_id": "3lJFkDheFKc1DgD3",
        "type": "ItemGrant",
        "configuration": {
          "items": [
            "Compendium.sw5e.speciesfeatures.VVeh66TfnPtkvO8N",
            "Compendium.sw5e.speciesfeatures.HtXYLhkTcxvul9gM",
            "Compendium.sw5e.speciesfeatures.YD63aRg6N227dDhT",
            "Compendium.sw5e.speciesfeatures.K2QZOIExNASJlRAM",
            "Compendium.sw5e.speciesfeatures.yXNY45InlhaDNYsc",
            "Compendium.sw5e.speciesfeatures.00qqGSh24CqpJiZK",
            "Compendium.sw5e.speciesfeatures.eo3ztEkIura8ZlPf",
            "Compendium.sw5e.speciesfeatures.g47CKLCofEff2b1H",
            "Compendium.sw5e.speciesfeatures.PyBOqmt6eYHPm2va",
            "Compendium.sw5e.speciesfeatures.b6AFSARAWcmSiM6l",
            "Compendium.sw5e.speciesfeatures.mLf5JTlns8KMmv5S"
          ],
          "optional": true
        },
        "value": {},
        "level": 0,
        "title": "Traits"
      },
      {
        "_id": "DtU52aLeslI12s2u",
        "type": "AbilityScoreImprovement",
        "configuration": {
          "fixed": {
            "str": 2,
            "con": 1
          },
          "points": 0
        },
        "value": {},
        "level": 0
      }
    ],
    "details": {
      "isDroid": false
    },
    "skinColorOptions": {
      "value": "Black or light to dark brown"
    },
    "hairColorOptions": {
      "value": "Black, light to dark brown, grey (usually with age)"
    },
    "eyeColorOptions": {
      "value": "Black or gray"
    },
    "colorScheme": {
      "value": null
    },
    "distinctions": {
      "value": "Lupine appearance, enhanced senses, increased speed, increased strength, healing ability"
    },
    "heightAverage": {
      "value": "5'7\""
    },
    "heightRollMod": {
      "value": "+2d8\""
    },
    "weightAverage": {
      "value": "140 lb."
    },
    "weightRollMod": {
      "value": "x(2d4) lb."
    },
    "homeworld": {
      "value": "Uvena Prime"
    },
    "slanguage": {
      "value": "Shistavanen"
    }
  },
  "ownership": {
    "default": 0
  },
  "_stats": {
    "systemId": "sw5e",
    "systemVersion": "2.3.1.2.6.4",
    "coreVersion": "11.308",
    "createdTime": 1674494002136,
    "modifiedTime": 1698794204429,
    "lastModifiedBy": "sw5ebuilder0000"
  },
  "_key": "!items!q77zsiObxfzRNWUF"
}
