{
  "name": "Darkness Charges",
  "flags": {
    "sw5e-importer": {
      "timestamp": "2023-03-09T01:52:14.6827392+00:00",
      "importer_version": 3,
      "uid": "Feature.name-darkness_charges.source-archetype.sourceName-kage_order.level-5"
    }
  },
  "type": "feat",
  "img": "systems/sw5e/packs/Icons/Class%20Features/MNK-ARCH-Passive.webp",
  "system": {
    "description": {
      "value": "<p><em><strong>Kage Order:</strong> 3rd, 5th, 9th, 13th, and 17th level</em></p>\n<p>You learn to create a number of small charges that create enhanced darkness. Over the course of a short or long rest, you can create two charges. You can create an additional charge at 5th, 9th, 13th, and 17th level. Your charges can only be used by you, and they lose their potency at the end of your next short or long rest.</p>\n<p>Once per turn, when you would make a weapon attack or unarmed strike, you can instead throw one of your charges. Your charges have a range equal to 30 feet + your Strength modifier x 5. You can throw a device at a point you can see within range. The charges create a pocket of darkness in a 10-foot radius sphere centered on that point. The darkness spreads around corners. It lasts for 1 minute or until an enhanced source of bright light dispells it.</p>",
      "chat": "",
      "unidentified": ""
    },
    "requirements": "Monk (Kage Order) 5",
    "source": "EC",
    "activation": {
      "type": "",
      "cost": null,
      "condition": ""
    },
    "duration": {
      "value": "1",
      "units": "minute"
    },
    "cover": null,
    "crewed": false,
    "target": {
      "value": 10,
      "width": null,
      "units": "ft",
      "type": "sphere"
    },
    "range": {
      "value": null,
      "long": null,
      "units": ""
    },
    "uses": {
      "value": null,
      "max": "",
      "per": null,
      "recovery": ""
    },
    "consume": {
      "type": "",
      "target": null,
      "amount": null
    },
    "ability": null,
    "actionType": "other",
    "attackBonus": "",
    "chatFlavor": "",
    "critical": {
      "threshold": null,
      "damage": ""
    },
    "damage": {
      "parts": [],
      "versatile": ""
    },
    "formula": "",
    "save": {
      "ability": "",
      "dc": null,
      "scaling": "power"
    },
    "type": {
      "value": "class",
      "subtype": ""
    },
    "recharge": {
      "value": null,
      "charged": false
    },
    "attributes": {
      "speed": {
        "space": 300,
        "turn": 250
      }
    }
  },
  "effects": [],
  "folder": null,
  "sort": 0,
  "ownership": {
    "default": 0
  },
  "_stats": {
    "systemId": "sw5e",
    "systemVersion": "2.3.1.2.6.4",
    "coreVersion": "11.315",
    "createdTime": 1680288495956,
    "modifiedTime": 1699591595176,
    "lastModifiedBy": "sw5ebuilder0000"
  },
  "_id": "TUkzSW9yzJaA9vMs",
  "_key": "!items!TUkzSW9yzJaA9vMs"
}
