{
  "_id": "AlQqDDigFMnrLi7h",
  "name": "Quickdraw",
  "type": "feat",
  "img": "systems/sw5e/packs/Icons/Class%20Features/OPRT-ARCH-Action.webp",
  "effects": [],
  "folder": null,
  "sort": 0,
  "flags": {
    "sw5e-importer": {
      "timestamp": "?",
      "importer_version": 3,
      "uid": "Feature.name-quickdraw.source-archetype.sourceName-gunslinger_practice.level-17"
    }
  },
  "system": {
    "description": {
      "value": "<p><em><strong>Gunslinger Practice:</strong> 17th level</em></p>\n<p>You learn to perform miracles with just a blaster and some nerve. On your first turn in combat, if you aren't surprised, you can use your action to attack creatures that have not yet acted. Choose up to six such creatures that you can see, making a ranged weapon attack against each. On a hit, you deal normal weapon damage and can apply a single trick shot to each attack made this way.</p>\n<p>Once you've used this feature, you must complete a short or long rest before you can use it again.</p>",
      "chat": "",
      "unidentified": ""
    },
    "requirements": "Operative (Gunslinger Practice) 17",
    "source": "EC",
    "activation": {
      "type": "action",
      "cost": 1,
      "condition": ""
    },
    "duration": {
      "value": null,
      "units": "inst"
    },
    "cover": null,
    "target": {
      "value": null,
      "width": null,
      "units": "",
      "type": ""
    },
    "range": {
      "value": null,
      "long": null,
      "units": "",
      "unit": ""
    },
    "uses": {
      "value": null,
      "max": 1,
      "per": "sr",
      "recovery": ""
    },
    "consume": {
      "type": "",
      "target": "",
      "amount": null
    },
    "ability": null,
    "actionType": "other",
    "attackBonus": 0,
    "chatFlavor": "",
    "critical": null,
    "damage": {
      "parts": [],
      "versatile": ""
    },
    "formula": "",
    "save": {
      "ability": "",
      "dc": null,
      "scaling": "power"
    },
    "type": {
      "value": "class",
      "subtype": ""
    },
    "recharge": {
      "value": null,
      "charged": false
    },
    "className": "Operative"
  },
  "ownership": {
    "default": 0
  },
  "_stats": {
    "systemId": "sw5e",
    "systemVersion": "2.1.5.2.4.0",
    "coreVersion": "10.291",
    "createdTime": 1674493957430,
    "modifiedTime": 1678471090696,
    "lastModifiedBy": "sw5ebuilder0000"
  }
}
