{
  "name": "Volley",
  "type": "feat",
  "img": "systems/sw5e/packs/Icons/Monster%20Traits/Volley.webp",
  "effects": [],
  "flags": {},
  "system": {
    "description": {
      "value": "<p>The <span style=\"font-family:'Open Sans', sans-serif\">{creature}</span> makes one ranged attack against every enemy within 10 feet of a point it can see.</p><section id=\"secret-UgdQSJ6IF2H3gIao\" class=\"secret\"><p><span style=\"font-family:'Open Sans'\"><em style=\"box-sizing:inherit;user-select:text;color:#1c1c1c;font-family:'Open Sans';font-size:12px\">Ranged Weapon Attack </em>+6, Range 100/400 ft., One target. <em style=\"box-sizing:inherit;user-select:text;color:#1c1c1c;font-family:'Open Sans';font-size:12px\">Hit : </em>8 (1d8+4) energy damage</span></p></section>",
      "chat": "",
      "unidentified": ""
    },
    "requirements": "",
    "source": "",
    "activation": {
      "type": "action",
      "cost": 1,
      "condition": ""
    },
    "duration": {
      "value": "",
      "units": ""
    },
    "cover": null,
    "target": {
      "value": 10,
      "width": null,
      "units": "ft",
      "type": "radius"
    },
    "range": {
      "value": 100,
      "long": 400,
      "units": ""
    },
    "uses": {
      "value": null,
      "max": "0",
      "per": "",
      "recovery": ""
    },
    "consume": {
      "type": "",
      "target": "",
      "amount": null
    },
    "ability": "",
    "actionType": "rwak",
    "attackBonus": "",
    "chatFlavor": "",
    "critical": {
      "threshold": null,
      "damage": ""
    },
    "damage": {
      "parts": [
        [
          "1d8 + @mod",
          "energy"
        ]
      ],
      "versatile": ""
    },
    "formula": "",
    "save": {
      "ability": "",
      "dc": null,
      "scaling": "power"
    },
    "type": {
      "value": "",
      "subtype": ""
    },
    "recharge": {
      "value": 6,
      "charged": true
    },
    "powercasting": {
      "force": "none",
      "tech": "none"
    }
  },
  "ownership": {
    "default": 0
  },
  "_stats": {
    "systemId": "sw5e",
    "systemVersion": "2.1.4.2.4.0",
    "coreVersion": "10.291",
    "createdTime": 1669754873892,
    "modifiedTime": 1677349726577,
    "lastModifiedBy": "sw5ebuilder0000"
  },
  "folder": null,
  "sort": 0,
  "_id": "NJ1N4jaSvO4Odl75"
}
