{
  "name": "Oyxgen tank",
  "flags": {
    "sw5e-importer": {
      "timestamp": "2023-05-30T20:15:25.5177592+00:00",
      "importer_version": 3,
      "uid": "Loot.name-oyxgen_tank.equipmentCategory-lifesupport"
    }
  },
  "type": "loot",
  "img": "systems/sw5e/packs/Icons/Life%20Support/OyxgenTank.webp",
  "system": {
    "description": {
      "value": null,
      "chat": "",
      "unidentified": ""
    },
    "requirements": "",
    "source": "EC",
    "quantity": 1,
    "weight": 20,
    "price": {
      "value": 100,
      "denomination": "gc"
    },
    "attunement": 0,
    "equipped": false,
    "rarity": "",
    "identified": true,
    "isCargo": false
  },
  "effects": [],
  "_id": "ddBIARJKv7kMTaLy",
  "folder": null,
  "sort": 0,
  "ownership": {
    "default": 0
  },
  "_stats": {
    "systemId": "sw5e",
    "systemVersion": "2.3.1.2.6.3",
    "coreVersion": "11.308",
    "createdTime": 1698185218976,
    "modifiedTime": 1698185218976,
    "lastModifiedBy": "sw5ebuilder0000"
  },
  "_key": "!items!ddBIARJKv7kMTaLy"
}
