{
  "_id": "VirrTNmszKdHDJ6H",
  "name": "Health Food",
  "type": "feat",
  "img": "systems/sw5e/packs/Icons/Class%20Features/SCLR-Passive.webp",
  "effects": [],
  "folder": null,
  "sort": 0,
  "flags": {
    "sw5e-importer": {
      "timestamp": "2023-03-09T01:52:15.1774524+00:00",
      "importer_version": 3,
      "uid": "Feature.name-health_food.source-archetypeinvocation.sourceName-chef_pursuit.level-None"
    }
  },
  "system": {
    "description": {
      "value": "<p>At the end of a short or long rest you may expend a superiority die and choose a number of friendly creatures up to your maneuver modifier (minimum of one), if they ate food you prepared. Each creature gains a number of temporary hit points equal to twice the number you roll on the superiority die. This maneuver has no effect on droids or constructs.</p>",
      "chat": "",
      "unidentified": ""
    },
    "requirements": "Scholar (Chef Pursuit)",
    "source": "EC",
    "activation": {
      "type": null,
      "cost": null,
      "condition": ""
    },
    "duration": {
      "value": null,
      "units": "inst"
    },
    "cover": null,
    "target": {
      "value": null,
      "width": null,
      "units": "",
      "type": ""
    },
    "range": {
      "value": null,
      "long": null,
      "units": "",
      "unit": ""
    },
    "uses": {
      "value": null,
      "max": null,
      "per": null,
      "recovery": ""
    },
    "consume": {
      "type": "",
      "target": null,
      "amount": null
    },
    "ability": null,
    "actionType": "other",
    "attackBonus": 0,
    "chatFlavor": "",
    "critical": {
      "threshold": null,
      "damage": ""
    },
    "damage": {
      "parts": [],
      "versatile": ""
    },
    "formula": "",
    "save": {
      "ability": "",
      "dc": null,
      "scaling": "power"
    },
    "type": {
      "value": "class",
      "subtype": "scholarInvocation"
    },
    "recharge": {
      "value": null,
      "charged": false
    },
    "attributes": {
      "speed": {
        "space": null,
        "turn": null
      }
    },
    "className": "Scholar"
  },
  "ownership": {
    "default": 0
  },
  "_stats": {
    "systemId": "sw5e",
    "systemVersion": "2.1.5.2.4.4",
    "coreVersion": "10.291",
    "createdTime": 1674493981111,
    "modifiedTime": 1684777308935,
    "lastModifiedBy": "sw5ebuilder0000"
  },
  "_key": "!items!VirrTNmszKdHDJ6H"
}
